pyquaca/__init__.py
pyquaca/api_requester.py
pyquaca/cache.py
pyquaca/json_cache.py
pyquaca/parser.py
pyquaca/py.typed
pyquaca/query.py
pyquaca/requester.py
pyquaca-0.0.4.dist-info/licenses/LICENSE
pyquaca-0.0.4.dist-info/METADATA
pyquaca-0.0.4.dist-info/WHEEL
pyquaca-0.0.4.dist-info/top_level.txt
pyquaca-0.0.4.dist-info/RECORD
